fibonacci/fibonacci.sv
/**
It is a series of numbers, where the next number is found by adding up the 2 numbers before it.
Series: 0, 1, 1, 2, 3, 5, 8, 13, 21, 34, 55, 89, 144,…
*/

/** Timescale */
`timescale 1ns/1ns

/** Main Module */
module fibonacci#(
		// Paramters
		parameter END_COUNT = 2, // end of the fibonacci Sequence
		parameter DUMP_NAME = "fibonacci_dump"
	)(
		// Ports
		input logic 		clk,    // Clock
		input logic 		rst,  	// Asynchronous reset active high
		output logic 		done,	//
		output logic [31:0] result	//
	);

	// Start by genertaing internal signals
	logic [31:0] current_value, prev_value;

	// Main counter
	always_ff @(posedge clk or posedge rst) begin : proc_
		if(rst) begin
			current_value 	<= 'd1;
			prev_value		<= 'd0;
		end else begin
			prev_value 		<= current_value;
			current_value	<= (current_value == END_COUNT) ? current_value : current_value + prev_value;
		end
	end

	// assign the end once the counter has reaced the END point
	assign done = (current_value == END_COUNT);

	// assign the result only once done
	assign result = (current_value)&({32{done}});

`ifdef COCOTB_SIM
	initial begin
	    $dumpfile({DUMP_NAME,".vcd"});
	    $dumpvars(0, fibonacci);
	end
`endif
endmodule // fibonacci

fibonacci/sim_build/END_COUNT=144,DUMP_NAME=fibonacci_dump/fibonacci_dump.vcd
$date
	Sun Jun  5 22:15:24 2022
$end
$version
	Icarus Verilog
$end
$timescale
	1ns
$end
$scope module fibonacci $end
$var wire 1 ! clk $end
$var wire 32 " result [31:0] $end
$var wire 1 # rst $end
$var wire 1 $ done $end
$var reg 32 % current_value [31:0] $end
$var reg 32 & prev_value [31:0] $end
$scope begin proc_ $end
$upscope $end
$upscope $end
$enddefinitions $end
#0
$dumpvars
bx &
bx %
x$
0#
bx "
0!
$end
#10
b0 "
b0 &
0$
b1 %
1#
#20
b1 &
0#
1!
#25
0!
#30
b10 %
1!
#35
0!
#40
b11 %
b10 &
1!
#45
0!
#50
b101 %
b11 &
1!
#55
0!
#60
b1000 %
b101 &
1!
#65
0!
#70
b1101 %
b1000 &
1!
#75
0!
#80
b10101 %
b1101 &
1!
#85
0!
#90
b100010 %
b10101 &
1!
#95
0!
#100
b110111 %
b100010 &
1!
#105
0!
#110
b1011001 %
b110111 &
1!
#115
0!
#120
b10010000 "
1$
b10010000 %
b1011001 &
1!
#125
0!
#130
b10010000 &
1!
