calculator/en_ff.sv
/** Enable Flop*/
/** Main Module */
module en_ff#(
		// Params
		parameter FF_WIDTH 			= 32,
		parameter NEGEDGE_SAMPLING 	= 0,
		parameter POSEDGE_SAMPLING 	= 1,
		parameter INITAL_VALUE		= 32'h0
	)
	(
		// Ports
		input logic ff_clk,
		input logic ff_rst,
		input logic ff_en,
		input logic [FF_WIDTH-1:0] ff_in_d,
		output logic [FF_WIDTH-1:0] ff_out_q,
		output logic [FF_WIDTH-1:0] ff_out_not_q
		);

`ifdef COCOTB_SIM
	// Asserts
	initial begin
		// Parameter checking
		assert(FF_WIDTH != 0) else $error("Flip Flop Data cannot be 0 FF_WIDTH");
		assert((NEGEDGE_SAMPLING ^ POSEDGE_SAMPLING) == 1) else $error("Cannot have a double EDGE sampling FF or a 0 edge sampling FF");
	end
`endif

	// Internal clocks
	logic l_clk;
	assign l_clk = (NEGEDGE_SAMPLING) ? ~ff_clk : ((POSEDGE_SAMPLING) ? ff_clk : 1'b0);

	// sample the output port
	logic [FF_WIDTH-1:0] q;
	always_ff @(posedge l_clk or posedge ff_rst) begin : proc_ip_calculation
		if(ff_rst) begin
			q <= INITAL_VALUE;
		end else if(ff_en) begin
			q <= ff_in_d;
		end
	end

	// Assign the not q data port
	assign ff_out_not_q = ~(q);
	assign ff_out_q 	= q;
endmodule

RV32I/pipe_ff.sv
/** Pipeline Flop*/
/** Main Module */
module pipe_ff#(
		// Params
		parameter FF_WIDTH 			= 32,
		parameter INITAL_VALUE		= 32'h0
	)
	(
		// Ports
		input 	logic stage_clk,
		input 	logic stage_rst,
		input 	logic [FF_WIDTH-1:0] stage_in_d,
		output 	logic [FF_WIDTH-1:0] stage_out_q
		);

`ifdef COCOTB_SIM
	// Asserts
	initial begin
		// Parameter checking
		assert(FF_WIDTH != 0) else $error("Flip Flop Data cannot be 0 FF_WIDTH");
	end
`endif

	// sample the output port
	logic [FF_WIDTH-1:0] q;
	always_ff @(posedge stage_clk or posedge stage_rst) begin : proc_stage
		if(stage_rst) begin
			q <= INITAL_VALUE;
		end else begin
			q <= stage_in_d;
		end
	end

	// Assign the not q data port
	assign stage_out_q = q;
endmodule

calculator/sqrt_c.sv
//Verilog function to find square root of a 32 bit number.
//The output is 16 bit.
module sqrt_c(
    // Ports
    input logic [31:0] op_in,
    output logic [31:0] op_out
);

    // internal signals.
    logic [31:0] a;
    logic [15:0] q;
    logic [17:0] l,r,re;    
    integer i;

    // Main combo loop Max 16 multiplier but not clock
    always_comb begin
        //initialize all the variables.
        a       = op_in;
        q       = 0;
        i       = 0;
        l       = 0;    //input to adder/sub
        r       = 0;    //input to adder/sub
        re      = 0;    //remainder
        //run the calculations for 16 iterations.
        for(i=0;i<16;i=i+1) begin 
            r       = {q,re[17],1'b1};
            l       = {re[15:0],a[31:30]};
            a       = {a[29:0],2'b00};    //left shift by 2 bits.
            if (re[17] == 1) 
                //add if r is negative
                re = l + r;
            else    
                //subtract if r is positive
                re = l - r;
            // Result
            q = {q[14:0],!re[17]};       
        end
    end

    // final assignment of output.
    assign op_out = q;   
endmodule // sqrt_c

calculator/calculator_piped.sv
/** */

/** Timescale */
`timescale 1ns/1ns

/** Opcode supported 
 * -> operations supported are:
 * SUM - MULT - SUB - SQRT - DIV*/
`ifdef COCOTB_SIM
	typedef enum logic [2:0] {
		SUM 	= 1,
		MULT 	= 2,
		SUB 	= 3,
		SQRT 	= 4,
		DIV 	= 5
	}cal_type_t;
`else 
	parameter SUM 	= 1;
	parameter MULT 	= 2;
	parameter SUB 	= 3;
	parameter SQRT 	= 4;
	parameter DIV 	= 5;
`endif 

/** Main Module */
module calculator_piped#(
		// Parameters
		parameter DW 			= 32,
`ifdef COCOTB_SIM				
		parameter DUMP_NAME 	= "calculator_piped_dump",
`endif
		parameter N_OF_STAGES 	= 3,
		parameter IS_PIPED 		= 1,
		parameter IS_FULLY_PIPED= 1
	)
	(
		// Ports
		input logic 			calc_clock,	//
		input logic 			calc_rst,	//
`ifdef COCOTB_SIM		
		input cal_type_t		opcode,		//
		input logic 			different,
`else 		
		input logic [2:0]		opcode,		//
`endif
		input logic [DW-1:0] 	op_in1, 	//
		input logic [DW-1:0] 	op_in2, 	//
		input logic 			op_in_sel, 	//
		output logic [2*DW-1:0] result, 	//
		output logic 			valid_res	//
	);

`ifdef COCOTB_SIM	
	initial begin
		// Parameter checker
		assert(~((IS_PIPED == 1) & (N_OF_STAGES == 0))) else $error("If RTL is piped number of STAGES cannot be 0");
		assert(~((IS_FULLY_PIPED == 1) & (IS_PIPED == 0))) else $error("If RTL is not piped CANNOT be Fully Piped");
	end
`endif

	/** FIRST STAGE PIPELINE ON INPUTS */
	logic [DW-1:0] op_in1_pipe;
	logic [DW-1:0] op_in2_pipe;
	logic op_in_sel_pipe;
`ifdef COCOTB_SIM		
	cal_type_t	opcode_pipe;
`else 		
	logic [2:0] opcode_pipe;
`endif

generate
if((IS_PIPED == 1) & (N_OF_STAGES > 0) & (IS_FULLY_PIPED ==1)) begin: first_stage_pipe
	pipe_ff#(DW,32'h0) u_op_in1_pipe(
		.stage_clk  (calc_clock),
		.stage_rst  (calc_rst),
		.stage_in_d (op_in1),
		.stage_out_q(op_in1_pipe));
	pipe_ff#(DW,32'h0) u_op_in2_pipe(
		.stage_clk  (calc_clock),
		.stage_rst  (calc_rst),
		.stage_in_d (op_in2),
		.stage_out_q(op_in2_pipe));
	pipe_ff#(1,1'b0) u_op_in_sel_pipe(
		.stage_clk  (calc_clock),
		.stage_rst  (calc_rst),
		.stage_in_d (op_in_sel),
		.stage_out_q(op_in_sel_pipe));	
	pipe_ff#(3,3'h0) u_opcode_pipe(
		.stage_clk  (calc_clock),
		.stage_rst  (calc_rst),
		.stage_in_d (opcode),
		.stage_out_q(opcode_pipe));		
end else begin
	assign op_in1_pipe 		= op_in1;
	assign op_in2_pipe 		= op_in2;
	assign op_in_sel_pipe 	= op_in_sel;
	assign opcode_pipe		= opcode;
end
endgenerate

	/** Internal Logic Signals */
	logic [2*DW-1:0] place_h_res, sampled_res;
	logic overflow;
	logic [DW-1:0] root_out;

	/** Main logic is under a fully combo logic */
	always_comb begin // op_selector
		place_h_res = {2*DW{1'b0}};
		case(opcode_pipe)
			SUM		: begin {overflow,place_h_res[DW-1:0]} 	= (op_in1_pipe + op_in2_pipe); end	
			MULT 	: begin {overflow,place_h_res} 			= (op_in1_pipe * op_in2_pipe);end
			SUB 	: begin {overflow,place_h_res[DW-1:0]} 	= (op_in1_pipe - op_in2_pipe); end	
			SQRT 	: begin {overflow,place_h_res[DW-1:0]} 	= root_out_pipe; end	
			DIV 	: begin {overflow,place_h_res} 			= {1'b0,{2*DW{1'b0}}}; end
			default	: begin {overflow,place_h_res} 			= {1'b0,{2*DW{1'b0}}}; end
		endcase // opcode
	end
	
	/** SECOND STAGE PIPELINE ON INTERMEDIATE SIGNALS */
	logic [2*DW-1:0] place_h_res_pipe;
	logic overflow_pipe;
generate
if((IS_PIPED == 1) & (N_OF_STAGES > 1) & (IS_FULLY_PIPED ==1)) begin: second_stage_pipe
	pipe_ff#(2*DW,{2*DW{1'b0}}) u_place_h_res_pipe(
		.stage_clk  (calc_clock),
		.stage_rst  (calc_rst),
		.stage_in_d (place_h_res),
		.stage_out_q(place_h_res_pipe));
	pipe_ff#(1,1'b0) u_overflow_pipe(
		.stage_clk  (calc_clock),
		.stage_rst  (calc_rst),
		.stage_in_d (overflow),
		.stage_out_q(overflow_pipe));
end else begin
	assign place_h_res_pipe = place_h_res;
	assign overflow_pipe 	= overflow;
end
endgenerate

	/** Sqaure root combo logic Huge area due to Multiplier */
	sqrt_c u_sqrt_c(
		.op_in (((op_in_sel_pipe) ? op_in1_pipe : op_in2_pipe)),
		.op_out(root_out));

	/** THIRD STAGE PIPELINE ON SQRT */
	logic [DW-1:0] root_out_pipe;
generate	
if((IS_PIPED == 1) & (N_OF_STAGES > 2) & (IS_FULLY_PIPED ==1)) begin: third_stage_pipe	
	pipe_ff#(DW,{DW{1'b0}}) u_root_out_pipe(
		.stage_clk  (calc_clock),
		.stage_rst  (calc_rst | (opcode != SQRT)),
		.stage_in_d (root_out),
		.stage_out_q(root_out_pipe));
end else begin
	assign root_out_pipe = (opcode == SQRT) ? root_out : {DW{1'b0}};
end
endgenerate

	/** Sample result only if there is no overflow*/
	en_ff#((2*DW),1'b0,1'b1,{2*DW{1'b0}}) u_ff_sampling(
		.ff_clk      (calc_clock),
		.ff_rst      (calc_rst),
		.ff_en       (~overflow_pipe),
		.ff_in_d     (place_h_res_pipe),
		.ff_out_q    (sampled_res),
		.ff_out_not_q());

	/** Assign valid result */
	assign int_valid 	= (~overflow_pipe) ? 1'b1 : 1'b0;

	/** zeroout the tresult in case of not valid */
	assign result 		= int_valid ? sampled_res : {2*DW{1'b0}};

	/** Valid POrt */
	assign valid_res 	= int_valid;

`ifdef COCOTB_SIM
	initial begin
	    $dumpfile({DUMP_NAME,".vcd"});
	    $dumpvars(0, calculator_piped);
	end
`endif
endmodule // calculator_piped

calculator/sim_build/DW=32,DUMP_NAME=calculator_piped_zero_dump,N_OF_STAGES=0,IS_PIPED=0,IS_FULLY_PIPED=0/calculator_piped_dump.vcd
$date
	Thu Jun  2 20:34:54 2022
$end
$version
	Icarus Verilog
$end
$timescale
	1ns
$end
$scope module calculator_piped $end
$var wire 1 ! calc_clock $end
$var wire 1 " calc_rst $end
$var wire 1 # different $end
$var wire 32 $ op_in1 [31:0] $end
$var wire 32 % op_in2 [31:0] $end
$var wire 1 & op_in_sel $end
$var wire 3 ' opcode [2:0] $end
$var wire 1 ( overflow_pipe $end
$var wire 1 ) valid_res $end
$var wire 64 * sampled_res [63:0] $end
$var wire 32 + root_out_pipe [31:0] $end
$var wire 32 , root_out [31:0] $end
$var wire 64 - result [63:0] $end
$var wire 64 . place_h_res_pipe [63:0] $end
$var wire 3 / opcode_pipe [2:0] $end
$var wire 1 0 op_in_sel_pipe $end
$var wire 32 1 op_in2_pipe [31:0] $end
$var wire 32 2 op_in1_pipe [31:0] $end
$var wire 1 3 int_valid $end
$var reg 1 ( overflow $end
$var reg 64 4 place_h_res [63:0] $end
$scope begin genblk2 $end
$upscope $end
$scope begin genblk4 $end
$upscope $end
$scope begin genblk6 $end
$upscope $end
$scope module u_ff_sampling $end
$var wire 1 ! ff_clk $end
$var wire 1 5 ff_en $end
$var wire 64 6 ff_in_d [63:0] $end
$var wire 64 7 ff_out_not_q [63:0] $end
$var wire 64 8 ff_out_q [63:0] $end
$var wire 1 " ff_rst $end
$var wire 1 9 l_clk $end
$var reg 64 : q [63:0] $end
$scope begin proc_ip_calculation $end
$upscope $end
$upscope $end
$scope module u_sqrt_c $end
$var wire 32 ; op_in [31:0] $end
$var wire 32 < op_out [31:0] $end
$var reg 32 = a [31:0] $end
$var reg 18 > l [17:0] $end
$var reg 16 ? q [15:0] $end
$var reg 18 @ r [17:0] $end
$var reg 18 A re [17:0] $end
$var integer 32 B i [31:0] $end
$upscope $end
$upscope $end
$enddefinitions $end
#0
$dumpvars
b10000 B
b111111111111111111 A
b11 @
b0 ?
b111111111111111100 >
b0 =
b0 <
b0 ;
bx :
09
bx 8
bx 7
b0 6
15
b0 4
13
b0 2
b0 1
00
b0 /
b0 .
bx -
b0 ,
b0 +
bx *
1)
0(
b0 '
0&
b0 %
b0 $
0#
0"
0!
$end
#10
b0 -
b1111111111111111111111111111111111111111111111111111111111111111 7
b0 *
b0 8
b0 :
1"
#20
0"
19
1!
#25
b101 ,
b101 <
b101 ?
b1010 A
b1011 @
b111111111111111111 >
b10000 B
b0 =
b1000100 .
b1000100 6
b1000100 4
b100011 ;
b1 /
b1 '
b100011 2
b100011 $
b100001 1
b100001 %
10
1&
09
0!
#30
b1000100 -
b1111111111111111111111111111111111111111111111111111111110111011 7
b1000100 *
b1000100 8
b1000100 :
19
1!
#35
09
0!
#40
19
1!
#45
09
0!
#50
19
1!
#55
09
0!
#60
19
1!
#65
b111111111111111110 A
b1101 @
b1011 >
b10000 B
b110 ,
b110 <
b110 ?
b0 =
b1000110100 .
b1000110100 6
b1000110100 4
b101111 ;
b10 /
b10 '
b1100 2
b1100 $
b101111 1
b101111 %
00
0&
09
0!
#70
b1000110100 -
b1111111111111111111111111111111111111111111111111111110111001011 7
b1000110100 *
b1000110100 8
b1000110100 :
19
1!
#75
09
0!
#80
19
1!
#85
09
0!
#90
19
1!
#95
09
0!
#100
19
1!
#105
b0 -
0)
03
05
b111111111111111110 A
b1011 @
b111111111111110011 >
b10000 B
b100 ,
b100 <
b100 ?
b0 =
1(
b11111111111111111111111111111100 .
b11111111111111111111111111111100 6
b11111111111111111111111111111100 4
b10111 ;
b11 /
b11 '
b10111 2
b10111 $
b11011 1
b11011 %
10
1&
09
0!
#110
19
1!
#115
09
0!
#120
19
1!
#125
09
0!
#130
19
1!
#135
09
0!
#140
19
1!
#145
b1000110100 -
1)
13
15
b110 +
b111111111111111100 A
b1101 @
b1001 >
b10000 B
b110 ,
b110 <
b110 ?
b0 =
0(
b110 .
b110 6
b110 4
b101101 ;
b100 /
b100 '
b111 2
b111 $
b101101 1
b101101 %
00
0&
09
0!
#150
b110 -
b1111111111111111111111111111111111111111111111111111111111111001 7
b110 *
b110 8
b110 :
19
1!
#155
09
0!
#160
19
1!
#165
09
0!
#170
19
1!
#175
09
0!
#180
19
1!
#185
b0 +
b111111111111111111 A
b1101 @
b1100 >
b10000 B
b110 ,
b110 <
b110 ?
b0 =
b0 .
b0 6
b0 4
b110000 ;
b101 /
b101 '
b110000 2
b110000 $
b1110 1
b1110 %
10
1&
09
0!
#190
b0 -
b1111111111111111111111111111111111111111111111111111111111111111 7
b0 *
b0 8
b0 :
19
1!
