calculator/en_ff.sv
/** Enable Flop*/
/** Main Module */
module en_ff#(
		// Params
		parameter FF_WIDTH 			= 32,
		parameter NEGEDGE_SAMPLING 	= 0,
		parameter POSEDGE_SAMPLING 	= 1,
		parameter INITAL_VALUE		= 32'h0
	)
	(
		// Ports
		input logic ff_clk,
		input logic ff_rst,
		input logic ff_en,
		input logic [FF_WIDTH-1:0] ff_in_d,
		output logic [FF_WIDTH-1:0] ff_out_q,
		output logic [FF_WIDTH-1:0] ff_out_not_q
		);

`ifdef COCOTB_SIM
	// Asserts
	initial begin
		// Parameter checking
		assert(FF_WIDTH != 0) else $error("Flip Flop Data cannot be 0 FF_WIDTH");
		assert((NEGEDGE_SAMPLING ^ POSEDGE_SAMPLING) == 1) else $error("Cannot have a double EDGE sampling FF or a 0 edge sampling FF");
	end
`endif

	// Internal clocks
	logic l_clk;
	assign l_clk = (NEGEDGE_SAMPLING) ? ~ff_clk : ((POSEDGE_SAMPLING) ? ff_clk : 1'b0);

	// sample the output port
	logic [FF_WIDTH-1:0] q;
	always_ff @(posedge l_clk or posedge ff_rst) begin : proc_ip_calculation
		if(ff_rst) begin
			q <= INITAL_VALUE;
		end else if(ff_en) begin
			q <= ff_in_d;
		end
	end

	// Assign the not q data port
	assign ff_out_not_q = ~(q);
	assign ff_out_q 	= q;
endmodule

calculator/sqrt_c.sv
//Verilog function to find square root of a 32 bit number.
//The output is 16 bit.
module sqrt_c(
    // Ports
    input logic [31:0] op_in,
    output logic [31:0] op_out
);

    // internal signals.
    logic [31:0] a;
    logic [15:0] q;
    logic [17:0] l,r,re;    
    integer i;

    // Main combo loop Max 16 multiplier but not clock
    always_comb begin
        //initialize all the variables.
        a       = op_in;
        q       = 0;
        i       = 0;
        l       = 0;    //input to adder/sub
        r       = 0;    //input to adder/sub
        re      = 0;    //remainder
        //run the calculations for 16 iterations.
        for(i=0;i<16;i=i+1) begin 
            r       = {q,re[17],1'b1};
            l       = {re[15:0],a[31:30]};
            a       = {a[29:0],2'b00};    //left shift by 2 bits.
            if (re[17] == 1) 
                //add if r is negative
                re = l + r;
            else    
                //subtract if r is positive
                re = l - r;
            // Result
            q = {q[14:0],!re[17]};       
        end
    end

    // final assignment of output.
    assign op_out = q;   
endmodule // sqrt_c

calculator/calculator.sv
/** */

/** Timescale */
`timescale 1ns/1ns

/** Opcode supported 
 * -> operations supported are:
 * SUM - MULT - SUB - SQRT - DIV*/
`ifdef COCOTB_SIM
	typedef enum logic [2:0] {
		SUM 	= 1,
		MULT 	= 2,
		SUB 	= 3,
		SQRT 	= 4,
		DIV 	= 5
	}cal_type_t;
`else 
	parameter SUM 	= 1;
	parameter MULT 	= 2;
	parameter SUB 	= 3;
	parameter SQRT 	= 4;
	parameter DIV 	= 5;
`endif 

/** Main Module */
module calculator#(
		// Parameters
`ifdef COCOTB_SIM				
		parameter DW = 32,
		parameter DUMP_NAME = "calculator_dump"
`else 
		parameter DW = 32
`endif
	)
	(
		// Ports
		input logic 			calc_clock,	//
		input logic 			calc_rst,	//
`ifdef COCOTB_SIM		
		input cal_type_t		opcode,		//
`else 		
		input logic [2:0]		opcode,		//
`endif
		input logic [DW-1:0] 	op_in1, 	//
		input logic [DW-1:0] 	op_in2, 	//
		input logic 			op_in_sel, 	//
		output logic [2*DW-1:0] result, 	//
		output logic 			valid_res	//
	);

	/** Internal Logic Signals */
	logic [2*DW-1:0] place_h_res;
	logic overflow;
	logic [DW-1:0] root_out;

	/** Main logic is under a fully combo logic */
	always_comb begin // op_selector
		place_h_res = {2*DW{1'b0}};
		case(opcode)
			SUM		: begin {overflow,place_h_res[DW-1:0]} 	= (op_in2 + op_in1); end	
			MULT 	: begin {overflow,place_h_res} 			= (op_in2 * op_in1);end
			SUB 	: begin {overflow,place_h_res[DW-1:0]} 	= (op_in2 - op_in1); end	
			SQRT 	: begin {overflow,place_h_res[DW-1:0]} 	= root_out; end	
			DIV 	: begin {overflow,place_h_res} 			= {1'b0,{2*DW{1'b0}}}; end
			default	: begin {overflow,place_h_res} 			= {1'b0,{2*DW{1'b0}}}; end
		endcase // opcode
	end

	/** Sqaure root combo logic Huge area due to Multiplier */
	sqrt_c u_sqrt_c(
		.op_in (op_in_sel ? op_in1 : op_in2),
		.op_out(root_out));

	/** Sample result only if there is no overflow*/
	en_ff#(2*DW,1'b0,1'b1,32'h0) u_ff_sampling(
		.ff_clk      (calc_clock),
		.ff_rst      (calc_rst),
		.ff_en       (~overflow),
		.ff_in_d     (place_h_res),
		.ff_out_q    (sampled_res),
		.ff_out_not_q());

	/** Assign valid result */
	assign int_valid = (~overflow) ? 1'b1 : 1'b0;

	/** zeroout the tresult in case of not valid */
	assign result = int_valid ? sampled_res : {2*DW{1'b0}};

	/** Valid POrt */
	assign valid_res = int_valid;

`ifdef COCOTB_SIM
	initial begin
	    $dumpfile({DUMP_NAME,".vcd"});
	    $dumpvars(0, calculator_piped);
	end
`endif
endmodule // calculator

calculator/sim_build/DW=32,DUMP_NAME=calculator_dump/calculator_dump.vcd
$date
	Thu Jun  2 17:52:16 2022
$end
$version
	Icarus Verilog
$end
$timescale
	1ns
$end
$scope module calculator $end
$var wire 1 ! calc_clock $end
$var wire 1 " calc_rst $end
$var wire 32 # op_in1 [31:0] $end
$var wire 32 $ op_in2 [31:0] $end
$var wire 1 % op_in_sel $end
$var wire 3 & opcode [2:0] $end
$var wire 1 ' valid_res $end
$var wire 64 ( sampled_res [63:0] $end
$var wire 32 ) root_out [31:0] $end
$var wire 64 * result [63:0] $end
$var wire 1 + int_valid $end
$var reg 1 , overflow $end
$var reg 64 - place_h_res [63:0] $end
$scope module u_ff_sampling $end
$var wire 1 ! ff_clk $end
$var wire 1 . ff_en $end
$var wire 64 / ff_in_d [63:0] $end
$var wire 64 0 ff_out_not_q [63:0] $end
$var wire 64 1 ff_out_q [63:0] $end
$var wire 1 " ff_rst $end
$var wire 1 2 l_clk $end
$var reg 64 3 q [63:0] $end
$scope begin proc_ip_calculation $end
$upscope $end
$upscope $end
$scope module u_sqrt_c $end
$var wire 32 4 op_in [31:0] $end
$var wire 32 5 op_out [31:0] $end
$var reg 32 6 a [31:0] $end
$var reg 18 7 l [17:0] $end
$var reg 16 8 q [15:0] $end
$var reg 18 9 r [17:0] $end
$var reg 18 : re [17:0] $end
$var integer 32 ; i [31:0] $end
$upscope $end
$upscope $end
$enddefinitions $end
#0
$dumpvars
b10000 ;
b111111111111111111 :
b11 9
b0 8
b111111111111111100 7
b0 6
b0 5
b0 4
bx 3
02
bx 1
bx 0
b0 /
1.
b0 -
0,
1+
bx *
b0 )
bx (
1'
b0 &
0%
b0 $
b0 #
0"
0!
$end
#10
b0 *
b1111111111111111111111111111111111111111111111111111111111111111 0
b0 (
b0 1
b0 3
1"
#20
0"
12
1!
#25
b10 )
b10 5
b10 8
b111111111111111011 :
b101 9
b0 7
b10000 ;
b0 6
b11101 -
b11101 /
b100 4
b1 &
b11001 #
b100 $
02
0!
#30
b11101 *
b1111111111111111111111111111111111111111111111111111111111100010 0
b11101 (
b11101 1
b11101 3
12
1!
#35
02
0!
#40
12
1!
#45
b111111111111110000 7
b111111111111111011 :
b1011 9
b10000 ;
b100 )
b100 5
b100 8
b0 6
b10001100 -
b10001100 /
b10100 4
b10 &
b111 #
b10100 $
02
0!
#50
b10001100 *
b1111111111111111111111111111111111111111111111111111111101110011 0
b10001100 (
b10001100 1
b10001100 3
12
1!
#55
02
0!
#60
12
1!
#65
b10 :
b1011 9
b111111111111110111 7
b10000 ;
b101 )
b101 5
b101 8
b0 6
b10000 -
b10000 /
b11011 4
b11 &
b11011 #
b101011 $
1%
02
0!
#70
b10000 *
b1111111111111111111111111111111111111111111111111111111111101111 0
b10000 (
b10000 1
b10000 3
12
1!
#75
02
0!
#80
12
1!
#85
b100 :
b1011 9
b111111111111111001 7
b10000 ;
b101 )
b101 5
b101 8
b0 6
b101 -
b101 /
b11101 4
b100 &
b10000 #
b11101 $
0%
02
0!
#90
b101 *
b1111111111111111111111111111111111111111111111111111111111111010 0
b101 (
b101 1
b101 3
12
1!
#95
02
0!
#100
12
1!
#105
b111111111111110101 :
b1101 9
b10 7
b10000 ;
b110 )
b110 5
b110 8
b0 6
b0 -
b0 /
b100110 4
b101 &
b100110 #
b110010 $
1%
02
0!
#110
b0 *
b1111111111111111111111111111111111111111111111111111111111111111 0
b0 (
b0 1
b0 3
12
1!
