fibonacci/clock_g.sv
/**
 * Clock gating is a way reducing dynamic Power dissipation by temporary turning-off clock of the Flops on certain parts of the logic or by turning-off 
 * enable on gated Flops. In other words, Flops are turned-on only if there is valid information to be stored or transferred. 
 * The accuracy with which these clocks are Turned-off is captured by clock gating efficiency
 */

/** Main Cell */
module clock_g (
	input 	logic clk_in,    	// Clock
	input 	logic clk_en, 		// Clock Enable
	output 	logic clock_out  	// Asynchronous reset active low
);
	// Internal signals
	logic clock_enable;
	// Start by stopping at the negedge
	always_latch  begin
 		if(~clk_in) 
    		clock_enable = clk_en;
	end
   	
   	// Gating without glitches
	assign clock_out = clk_in & clock_enable;
endmodule // clock_g

RV32I/pipe_ff.sv
/** Pipeline Flop*/
/** Main Module */
module pipe_ff#(
		// Params
		parameter FF_WIDTH 			= 32,
		parameter INITAL_VALUE		= 32'h0
	)
	(
		// Ports
		input 	logic stage_clk,
		input 	logic stage_rst,
		input 	logic [FF_WIDTH-1:0] stage_in_d,
		output 	logic [FF_WIDTH-1:0] stage_out_q
		);

`ifdef COCOTB_SIM
	// Asserts
	initial begin
		// Parameter checking
		assert(FF_WIDTH != 0) else $error("Flip Flop Data cannot be 0 FF_WIDTH");
	end
`endif

	// sample the output port
	logic [FF_WIDTH-1:0] q;
	always_ff @(posedge stage_clk or posedge stage_rst) begin : proc_stage
		if(stage_rst) begin
			q <= INITAL_VALUE;
		end else begin
			q <= stage_in_d;
		end
	end

	// Assign the not q data port
	assign stage_out_q = q;
endmodule

fibonacci/fibonacci_piped.sv
/**
It is a series of numbers, where the next number is found by adding up the 2 numbers before it.
Series: 0, 1, 1, 2, 3, 5, 8, 13, 21, 34, 55, 89, 144,…
*/

/** Timescale */
`timescale 1ns/1ns

/** Main Module */
module fibonacci_piped#(
		// Paramters
		parameter END_COUNT = 2, // end of the fibonacci Sequence
		parameter DUMP_NAME = "fibonacci_piped_dump"
	)(
		// Ports
		input logic 		clk,    // Clock
		input logic 		rst,  	// Asynchronous reset active high
		output logic 		done,	//
		output logic [31:0] result	//
	);

	// Start by genertaing internal signals
	logic [31:0] current_value;
	logic [31:0] prev_value;
	logic [31:0] result_pided;
	logic done_piped;
	logic gated_clk;

	// Main counter
	always_ff @(posedge clk or posedge rst) begin : proc_
		if(rst) begin
			current_value 	<= 32'h1;
			prev_value		<= 32'h0;
		end else begin
			prev_value 		<= current_value;
			current_value	<= (current_value == END_COUNT) ? current_value : current_value + prev_value;
		end
	end

	/** This is the only stage of Pipeline needed since the internal values are already flopped these are more like EN_FF */
	pipe_ff#(32,32'h0) result_pided_ff(
		.stage_clk  (gated_clk),
		.stage_rst  (~(current_value == END_COUNT)),
		.stage_in_d (current_value),
		.stage_out_q(result_pided));

	pipe_ff#(1,1'h0) done_piped_ff(
		.stage_clk  (gated_clk),
		.stage_rst  (~(current_value == END_COUNT)),
		.stage_in_d ((current_value == END_COUNT)),
		.stage_out_q(done_piped));

	/** Clock gating cell */
	clock_g clock_gating_cell(
		.clk_en   ((current_value == END_COUNT)),
		.clk_in   (clk),
		.clock_out(gated_clk));

	// assign the end once the counter has reaced the END point
	assign done = done_piped;

	// assign the result only once done
	assign result = result_pided;

`ifdef COCOTB_SIM
	initial begin
	    $dumpfile({DUMP_NAME,".vcd"});
	    $dumpvars(0, fibonacci_piped);
	end
`endif
endmodule // fibonacci_piped

fibonacci/sim_build/END_COUNT=144,DUMP_NAME=fibonacci_piped_dump/fibonacci_piped_dump.vcd
$date
	Sun Jun  5 22:15:24 2022
$end
$version
	Icarus Verilog
$end
$timescale
	1ns
$end
$scope module fibonacci_piped $end
$var wire 1 ! clk $end
$var wire 1 " done $end
$var wire 32 # result [31:0] $end
$var wire 1 $ rst $end
$var wire 32 % result_pided [31:0] $end
$var wire 1 & gated_clk $end
$var wire 1 ' done_piped $end
$var reg 32 ( current_value [31:0] $end
$var reg 32 ) prev_value [31:0] $end
$scope module clock_gating_cell $end
$var wire 1 * clk_en $end
$var wire 1 ! clk_in $end
$var wire 1 & clock_out $end
$var reg 1 + clock_enable $end
$upscope $end
$scope module done_piped_ff $end
$var wire 1 & stage_clk $end
$var wire 1 , stage_in_d $end
$var wire 1 ' stage_out_q $end
$var wire 1 - stage_rst $end
$var reg 1 ' q $end
$scope begin proc_stage $end
$upscope $end
$upscope $end
$scope module result_pided_ff $end
$var wire 1 & stage_clk $end
$var wire 32 . stage_in_d [31:0] $end
$var wire 32 / stage_out_q [31:0] $end
$var wire 1 0 stage_rst $end
$var reg 32 1 q [31:0] $end
$scope begin proc_stage $end
$upscope $end
$upscope $end
$scope begin proc_ $end
$upscope $end
$upscope $end
$enddefinitions $end
#0
$dumpvars
bx 1
x0
bx /
bx .
x-
x,
x+
x*
bx )
bx (
x'
0&
bx %
0$
bx #
x"
0!
$end
#10
b0 #
b0 %
b0 /
b0 1
0"
0'
10
1-
0+
b0 )
0,
0*
b1 (
b1 .
1$
#20
b1 )
0$
1!
#25
0!
#30
b10 (
b10 .
1!
#35
0!
#40
b11 (
b11 .
b10 )
1!
#45
0!
#50
b101 (
b101 .
b11 )
1!
#55
0!
#60
b1000 (
b1000 .
b101 )
1!
#65
0!
#70
b1101 (
b1101 .
b1000 )
1!
#75
0!
#80
b10101 (
b10101 .
b1101 )
1!
#85
0!
#90
b100010 (
b100010 .
b10101 )
1!
#95
0!
#100
b110111 (
b110111 .
b100010 )
1!
#105
0!
#110
b1011001 (
b1011001 .
b110111 )
1!
#115
0!
#120
00
0-
1,
1*
b10010000 (
b10010000 .
b1011001 )
1!
#125
1+
0!
#130
1"
1'
b10010000 #
b10010000 %
b10010000 /
b10010000 1
b10010000 )
1&
1!
