fibonacci/fibonacci.sv
/**
It is a series of numbers, where the next number is found by adding up the 2 numbers before it.
Series: 0, 1, 1, 2, 3, 5, 8, 13, 21, 34, 55, 89, 144,…
*/

/** Timescale */
`timescale 1ns/1ns

/** Main Module */
module fibonacci#(
		// Paramters
		parameter END_COUNT = 2, // end of the fibonacci Sequence
		parameter DUMP_NAME = "fibonacci_dump"
	)(
		// Ports
		input logic 		clk,    // Clock
		input logic 		rst,  	// Asynchronous reset active high
		output logic 		done,	//
		output logic [31:0] result	//
	);

	// Start by genertaing internal signals
	logic [31:0] current_value, prev_value;

	// Main counter
	always_ff @(posedge clk or posedge rst) begin : proc_
		if(rst) begin
			current_value 	<= 'd1;
			prev_value		<= 'd0;
		end else begin
			prev_value 		<= current_value;
			current_value	<= (current_value == END_COUNT) ? current_value : current_value + prev_value;
		end
	end

	// assign the end once the counter has reaced the END point
	assign done = (current_value == END_COUNT);

	// assign the result only once done
	assign result = (current_value)&({32{done}});

`ifdef COCOTB_SIM
	initial begin
	    $dumpfile({DUMP_NAME,".vcd"});
	    $dumpvars(0, fibonacci);
	end
`endif
endmodule // fibonacci

fibonacci/sim_build/END_COUNT=142,DUMP_NAME=fibonacci_dump/fibonacci_dump.vcd
$date
	Sun Jun  5 21:54:01 2022
$end
$version
	Icarus Verilog
$end
$timescale
	1ns
$end
$scope module fibonacci $end
$var wire 1 ! clk $end
$var wire 32 " result [31:0] $end
$var wire 1 # rst $end
$var wire 1 $ done $end
$var reg 32 % current_value [31:0] $end
$var reg 32 & prev_value [31:0] $end
$scope begin proc_ $end
$upscope $end
$upscope $end
$enddefinitions $end
#0
$dumpvars
bx &
bx %
x$
0#
bx "
0!
$end
#10
b0 "
b0 &
0$
b1 %
1#
#20
b1 &
0#
1!
#25
0!
#30
b10 %
1!
#35
0!
#40
b11 %
b10 &
1!
#45
0!
#50
b101 %
b11 &
1!
#55
0!
#60
b1000 %
b101 &
1!
#65
0!
#70
b1101 %
b1000 &
1!
#75
0!
#80
b10101 %
b1101 &
1!
#85
0!
#90
b100010 %
b10101 &
1!
#95
0!
#100
b110111 %
b100010 &
1!
#105
0!
#110
b1011001 %
b110111 &
1!
#115
0!
#120
b10010000 %
b1011001 &
1!
#125
0!
#130
b11101001 %
b10010000 &
1!
#135
0!
#140
b101111001 %
b11101001 &
1!
#145
0!
#150
b1001100010 %
b101111001 &
1!
#155
0!
#160
b1111011011 %
b1001100010 &
1!
#165
0!
#170
b11000111101 %
b1111011011 &
1!
#175
0!
#180
b101000011000 %
b11000111101 &
1!
#185
0!
#190
b1000001010101 %
b101000011000 &
1!
#195
0!
#200
b1101001101101 %
b1000001010101 &
1!
#205
0!
#210
b10101011000010 %
b1101001101101 &
1!
#215
0!
#220
b100010100101111 %
b10101011000010 &
1!
#225
0!
#230
b110111111110001 %
b100010100101111 &
1!
#235
0!
#240
b1011010100100000 %
b110111111110001 &
1!
#245
0!
#250
b10010010100010001 %
b1011010100100000 &
1!
#255
0!
#260
b11101101000110001 %
b10010010100010001 &
1!
#265
0!
#270
b101111111101000010 %
b11101101000110001 &
1!
#275
0!
#280
b1001101100101110011 %
b101111111101000010 &
1!
#285
0!
#290
b1111101100010110101 %
b1001101100101110011 &
1!
#295
0!
#300
b11001011001000101000 %
b1111101100010110101 &
1!
#305
0!
#310
b101001000101011011101 %
b11001011001000101000 &
1!
#315
0!
#320
b1000010011110100000101 %
b101001000101011011101 &
1!
#325
0!
#330
b1101011100011111100010 %
b1000010011110100000101 &
1!
#335
0!
#340
b10101110000010011100111 %
b1101011100011111100010 &
1!
#345
0!
#350
b100011001100110011001001 %
b10101110000010011100111 &
1!
#355
0!
#360
b111000111101000110110000 %
b100011001100110011001001 &
1!
#365
0!
#370
b1011100001001111001111001 %
b111000111101000110110000 &
1!
#375
0!
#380
b10010101000111000000101001 %
b1011100001001111001111001 &
1!
#385
0!
#390
b11110001010000111010100010 %
b10010101000111000000101001 &
1!
#395
0!
#400
b110000110010111111011001011 %
b11110001010000111010100010 &
1!
#405
0!
#410
b1001110111101000110101101101 %
b110000110010111111011001011 &
1!
#415
0!
#420
b1111111110000000110000111000 %
b1001110111101000110101101101 &
1!
#425
0!
#430
b11001110101101001100110100101 %
b1111111110000000110000111000 &
1!
#435
0!
#440
b101001110011101010010111011101 %
b11001110101101001100110100101 &
1!
#445
0!
#450
b1000011101001010011111110000010 %
b101001110011101010010111011101 &
1!
#455
0!
#460
b1101101011100111110010101011111 %
b1000011101001010011111110000010 &
1!
#465
0!
#470
b10110001000110010010010011100001 %
b1101101011100111110010101011111 &
1!
#475
0!
#480
b11110100011010000101001000000 %
b10110001000110010010010011100001 &
1!
#485
0!
#490
b11001111101001100010111100100001 %
b11110100011010000101001000000 &
1!
#495
0!
#500
b11101110001100110011100101100001 %
b11001111101001100010111100100001 &
1!
#505
0!
#510
b10111101110110010110100010000010 %
b11101110001100110011100101100001 &
1!
#515
0!
#520
b10101100000011001010000111100011 %
b10111101110110010110100010000010 &
1!
#525
0!
#530
b1101001111001100000101001100101 %
b10101100000011001010000111100011 &
1!
#535
0!
#540
b10101111100101010110001001000 %
b1101001111001100000101001100101 &
1!
#545
0!
#550
b1111111110110001011011010101101 %
b10101111100101010110001001000 &
1!
#555
0!
#560
b10010101110010110110001011110101 %
b1111111110110001011011010101101 &
1!
#565
0!
#570
b10101101001000001100110100010 %
b10010101110010110110001011110101 &
1!
#575
0!
#580
b10101011011011110111110010010111 %
b10101101001000001100110100010 &
1!
#585
0!
#590
b11000001000100111001011000111001 %
b10101011011011110111110010010111 &
1!
#595
0!
#600
b1101100100000110001001011010000 %
b11000001000100111001011000111001 &
1!
#605
0!
#610
b101101100101101010100100001001 %
b1101100100000110001001011010000 &
1!
#615
0!
#620
b10011010000110011011101111011001 %
b101101100101101010100100001001 &
1!
#625
0!
#630
b11000111101100000110010011100010 %
b10011010000110011011101111011001 &
1!
#635
0!
#640
b1100001110010100010000010111011 %
b11000111101100000110010011100010 &
1!
#645
0!
#650
b101001011110101000010110011101 %
b1100001110010100010000010111011 &
1!
#655
0!
#660
b10001011010001001010011001011000 %
b101001011110101000010110011101 &
1!
#665
0!
#670
b10110100101111110010101111110101 %
b10001011010001001010011001011000 &
1!
#675
0!
#680
b1000000000000111101001001001101 %
b10110100101111110010101111110101 &
1!
#685
0!
#690
b11110100110000101111111001000010 %
b1000000000000111101001001001101 &
1!
#695
0!
#700
b110100110001101101000010001111 %
b11110100110000101111111001000010 &
1!
#705
0!
#710
b101001100010011100111011010001 %
b110100110001101101000010001111 &
1!
#715
0!
#720
b1011110010100001001111101100000 %
b101001100010011100111011010001 &
1!
#725
0!
#730
b10000111110110100110111000110001 %
b1011110010100001001111101100000 &
1!
#735
0!
#740
b11100110001010110000110110010001 %
b10000111110110100110111000110001 &
1!
#745
0!
#750
b1101110000001010111101111000010 %
b11100110001010110000110110010001 &
1!
#755
0!
#760
b1010100001100001000100101010011 %
b1101110000001010111101111000010 &
1!
#765
0!
#770
b11000010001101100000010100010101 %
b1010100001100001000100101010011 &
1!
#775
0!
#780
b10110011001101000111001101000 %
b11000010001101100000010100010101 &
1!
#785
0!
#790
b11011000100111001001001101111101 %
b10110011001101000111001101000 &
1!
#795
0!
#800
b11101111000000110010000111100101 %
b11011000100111001001001101111101 &
1!
#805
0!
#810
b11000111100111111011010101100010 %
b11101111000000110010000111100101 &
1!
#815
0!
#820
b10110110101000101101011101000111 %
b11000111100111111011010101100010 &
1!
#825
0!
#830
b1111110010000101000110010101001 %
b10110110101000101101011101000111 &
1!
#835
0!
#840
b110100111001010110001111110000 %
b1111110010000101000110010101001 &
1!
#845
0!
#850
b10110011001001111111000010011001 %
b110100111001010110001111110000 &
1!
#855
0!
#860
b11101000000011010101010010001001 %
b10110011001001111111000010011001 &
1!
#865
0!
#870
b10011011001101010100010100100010 %
b11101000000011010101010010001001 &
1!
#875
0!
#880
b10000011010000101001100110101011 %
b10011011001101010100010100100010 &
1!
#885
0!
#890
b11110011101111101111011001101 %
b10000011010000101001100110101011 &
1!
#895
0!
#900
b10100001101110100111100001111000 %
b11110011101111101111011001101 &
1!
#905
0!
#910
b11000000001100100101011101000101 %
b10100001101110100111100001111000 &
1!
#915
0!
#920
b1100001111011001100111110111101 %
b11000000001100100101011101000101 &
1!
#925
0!
#930
b100010000111110010011100000010 %
b1100001111011001100111110111101 &
1!
#935
0!
#940
b10000100000010111111011010111111 %
b100010000111110010011100000010 &
1!
#945
0!
#950
b10100110001010110001110111000001 %
b10000100000010111111011010111111 &
1!
#955
0!
#960
b101010001101110001010010000000 %
b10100110001010110001110111000001 &
1!
#965
0!
#970
b11010000011000100011001001000001 %
b101010001101110001010010000000 &
1!
#975
0!
#980
b11111010100110010100011011000001 %
b11010000011000100011001001000001 &
1!
#985
0!
#990
b11001010111110110111100100000010 %
b11111010100110010100011011000001 &
1!
#995
0!
#1000
b11000101100101001011111111000011 %
b11001010111110110111100100000010 &
1!
#1005
0!
#1010
b10010000100100000011100011000101 %
b11000101100101001011111111000011 &
1!
