calculator/en_ff.sv
/** Enable Flop*/
/** Main Module */
module en_ff#(
		// Params
		parameter FF_WIDTH 			= 32,
		parameter NEGEDGE_SAMPLING 	= 0,
		parameter POSEDGE_SAMPLING 	= 1,
		parameter INITAL_VALUE		= 32'h0
	)
	(
		// Ports
		input logic ff_clk,
		input logic ff_rst,
		input logic ff_en,
		input logic [FF_WIDTH-1:0] ff_in_d,
		output logic [FF_WIDTH-1:0] ff_out_q,
		output logic [FF_WIDTH-1:0] ff_out_not_q
		);

`ifdef COCOTB_SIM
	// Asserts
	initial begin
		// Parameter checking
		assert(FF_WIDTH != 0) else $error("Flip Flop Data cannot be 0 FF_WIDTH");
		assert((NEGEDGE_SAMPLING ^ POSEDGE_SAMPLING) == 1) else $error("Cannot have a double EDGE sampling FF or a 0 edge sampling FF");
	end
`endif

	// Internal clocks
	logic l_clk;
	assign l_clk = (NEGEDGE_SAMPLING) ? ~ff_clk : ((POSEDGE_SAMPLING) ? ff_clk : 1'b0);

	// sample the output port
	logic [FF_WIDTH-1:0] q;
	always_ff @(posedge l_clk or posedge ff_rst) begin : proc_ip_calculation
		if(ff_rst) begin
			q <= INITAL_VALUE;
		end else if(ff_en) begin
			q <= ff_in_d;
		end
	end

	// Assign the not q data port
	assign ff_out_not_q = ~(q);
	assign ff_out_q 	= q;
endmodule

fibonacci/clock_g.sv
/**
 * Clock gating is a way reducing dynamic Power dissipation by temporary turning-off clock of the Flops on certain parts of the logic or by turning-off 
 * enable on gated Flops. In other words, Flops are turned-on only if there is valid information to be stored or transferred. 
 * The accuracy with which these clocks are Turned-off is captured by clock gating efficiency
 */

/** Main Cell */
module clock_g (
	input 	logic clk_in,    	// Clock
	input 	logic clk_en, 		// Clock Enable
	output 	logic clock_out  	// Asynchronous reset active low
);
	// Internal signals
	logic clock_enable;
	// Start by stopping at the negedge
	always_latch  begin
 		if(~clk_in) 
    		clock_enable = clk_en;
	end
   	
   	// Gating without glitches
	assign clock_out = clk_in & clock_enable;
endmodule // clock_g

pythagora_theorem/sqrt_int.sv
/** ALGORITHM for a no FP computation
 *      1  0  1  1     Our answer: one digit for each pair of digits in the radicand
    ———————————
   √01 11 10 01     Our radicand

    01              Bring down the most significant pair
  - 01              Subtract 01
    ——
    00              Our answer is NOT negative, so our first answer digit is 1

    00 11           Bring down the next pair of digits and append to previous result
  - 01 01           Append 01 to our existing answer, 1, and subtract it
    —————
    11 00           Our result is negative, so our second answer digit is 0
                    We discard the result because it's negative

    00 11 10        Keep the existing digits, 00 11, and append the next pair
  -    10 01        Append 01 to our existing answer, 10, and subtract it
    ————————
       01 01        Our answer is NOT negative, so our next answer digit is 1

       01 01 01     Bring down the next pair of digits and append to previous result
    -  01 01 01     Append 01 to our existing answer, 101, and subtract it
       ————————
             00     Our answer is NOT negative, so our next answer digit is 1
*/

/** Main Module */
module sqrt_int #(
    parameter WIDTH = 8              // width of radicand
) (
    input   logic clk,
    input   logic start,             // start signal
    output  logic busy,              // calculation in progress
    output  logic valid,             // root and rem are valid
    input   logic [WIDTH-1:0] rad,   // radicand
    output  logic [WIDTH-1:0] root,  // root
    output  logic [WIDTH-1:0] rem    // remainder
);

    logic [WIDTH-1:0] x, x_next;    // radicand copy
    logic [WIDTH-1:0] q, q_next;    // intermediate root (quotient)
    logic [WIDTH+1:0] ac, ac_next;  // accumulator (2 bits wider)
    logic [WIDTH+1:0] test_res;     // sign test result (2 bits wider)

    localparam ITER = WIDTH >> 1;   // iterations are half radicand width
    logic [$clog2(ITER)-1:0] i;     // iteration counter

    always_comb begin
        test_res = ac - {q, 2'b01};
        if (test_res[WIDTH+1] == 0) begin  // test_res ≥0? (check MSB)
            {ac_next, x_next} = {test_res[WIDTH-1:0], x, 2'b0};
            q_next = {q[WIDTH-2:0], 1'b1};
        end else begin
            {ac_next, x_next} = {ac[WIDTH-1:0], x, 2'b0};
            q_next = q << 1;
        end
    end

    always_ff @(posedge clk) begin
        if (start) begin
            busy <= 1;
            valid <= 0;
            i <= 0;
            q <= 0;
            {ac, x} <= {{WIDTH{1'b0}}, rad, 2'b0};
        end else if (busy) begin
            if (i == ITER-1) begin  // we're done
                busy <= 0;
                valid <= 1;
                root <= q_next;
                rem <= ac_next[WIDTH+1:2];  // undo final shift
            end else begin  // next iteration
                i <= i + 1;
                x <= x_next;
                ac <= ac_next;
                q <= q_next;
            end
        end
    end
endmodule

pythagora_theorem/pythagora_th.sv
/** Module:
 * For a right-angled triangle, the area of the square of the hypotenuse is equal to the sum of the areas of the squares on the other two sides.
 */


/** Time scale */
`timescale 1us/1ns

/** Main Module*/
module pythagora_th#(
		// Parameters
		parameter DW = 32
	)
	(
		// Ports
		input logic 	py_clock,		//
		input logic 	py_rst,			//
		input logic 	py_start,		//
		input logic [DW-1:0] py_s0,		//
		input logic [DW-1:0] py_s1,		//
		output logic [DW-1:0] py_hyp,	//
		output logic py_valid);			//

	/** Internal logic signals */
	logic en_condition;
	logic [DW-1:0] sum_in;
	logic [DW-1:0] int_reminder;
	logic [DW-1:0] int_root;
	logic [DW-1:0] sampled_root;
	logic qualified_start;
	logic overflow;
	logic int_busy;
	logic int_valid;
	logic gated_clock;

	/** Assign the sum of each side power of 2 */
	assign {overflow,sum_in} = ((py_s0*py_s0) + (py_s1*py_s1));

	/** Assign the qualified start which must be 0 if we overflow so that the SQRT doesn't start */
	assign qualified_start = py_start & (~overflow);

	/** SQRT istance */
	sqrt_int#(DW) u_sqrt(
		.clk  (py_clock),
		.start(qualified_start),
		.busy (int_busy),
		.valid(int_valid),
		.rad  (sum_in),
		.root (int_root),
		.rem  (int_reminder)); 

	/** Evaluate the enabling clock condition 
	 * Enable clock if:
	 * -> we are not overflowing
	 * -> each side must be different from 0
	 * -> we are not under reset
	 * -> the SQRT logic is no busy
	 * */
	assign en_condition = (~overflow) & ((|py_s0) != 1'b0) & ((|py_s1) != 1'b0) & (~py_rst) & (~int_busy);

	/** Clock Gating Cell for sampling clock*/
	clock_g u_clock_gating_cell(
		.clk_in   (py_clock),
		.clk_en   (en_condition),
		.clock_out(gated_clock));

	/** Sampling logic */
	en_ff#(DW,1'b0,1'b1,32'h0) u_hypo_sampling(
			.ff_clk      (gated_clock),
			.ff_rst      (py_rst),
			.ff_en       (int_valid),
			.ff_in_d     (int_root),
			.ff_out_q    (sampled_root),
			.ff_out_not_q());

	/** Assign the output */
	assign py_hyp = sampled_root;

	/** Assign Valid signal */
	assign py_valid = int_valid;
	
`ifdef COCOTB_SIM
	initial begin
	  $dumpfile ("dump.vcd");
	  $dumpvars (0, pythagora_th);
	end
`endif	
endmodule // pythagora_th

pythagora_theorem/sim_build/DW=32/dump.vcd
$date
	Thu Jun  2 16:05:30 2022
$end
$version
	Icarus Verilog
$end
$timescale
	1ns
$end
$scope module pythagora_th $end
$var wire 1 ! en_condition $end
$var wire 1 " py_clock $end
$var wire 32 # py_hyp [31:0] $end
$var wire 1 $ py_rst $end
$var wire 32 % py_s0 [31:0] $end
$var wire 32 & py_s1 [31:0] $end
$var wire 1 ' py_start $end
$var wire 1 ( py_valid $end
$var wire 1 ) qualified_start $end
$var wire 32 * sum_in [31:0] $end
$var wire 32 + sampled_root [31:0] $end
$var wire 1 , overflow $end
$var wire 1 - int_valid $end
$var wire 32 . int_root [31:0] $end
$var wire 32 / int_reminder [31:0] $end
$var wire 1 0 int_busy $end
$var wire 1 1 gated_clock $end
$scope module u_clock_gating_cell $end
$var wire 1 ! clk_en $end
$var wire 1 " clk_in $end
$var wire 1 1 clock_out $end
$var reg 1 2 clock_enable $end
$upscope $end
$scope module u_hypo_sampling $end
$var wire 1 1 ff_clk $end
$var wire 32 3 ff_out_not_q [31:0] $end
$var wire 32 4 ff_out_q [31:0] $end
$var wire 1 $ ff_rst $end
$var wire 1 5 l_clk $end
$var wire 32 6 ff_in_d [31:0] $end
$var wire 1 - ff_en $end
$var reg 32 7 q [31:0] $end
$scope begin proc_ip_calculation $end
$upscope $end
$upscope $end
$scope module u_sqrt $end
$var wire 1 " clk $end
$var wire 32 8 rad [31:0] $end
$var wire 1 ) start $end
$var reg 34 9 ac [33:0] $end
$var reg 34 : ac_next [33:0] $end
$var reg 1 0 busy $end
$var reg 4 ; i [3:0] $end
$var reg 32 < q [31:0] $end
$var reg 32 = q_next [31:0] $end
$var reg 32 > rem [31:0] $end
$var reg 32 ? root [31:0] $end
$var reg 34 @ test_res [33:0] $end
$var reg 1 - valid $end
$var reg 32 A x [31:0] $end
$var reg 32 B x_next [31:0] $end
$upscope $end
$upscope $end
$enddefinitions $end
#0
$dumpvars
bx00 B
bx A
bx @
bx ?
bx >
bx0 =
bx <
bx ;
bx :
bx 9
b0 8
bx 7
bx 6
05
bx 4
bx 3
02
01
x0
bx /
bx .
x-
0,
bx +
b0 *
0)
x(
0'
b0 &
b0 %
0$
bx #
0"
0!
$end
#10
b11111111111111111111111111111111 3
b0 #
b0 +
b0 4
b0 7
1$
#20
x!
b100111000100 *
b100111000100 8
1)
b11110 %
b101000 &
1'
0$
1"
#25
x2
0"
#30
0)
0'
0!
b0 =
b0 :
b1001110001000000 B
b1111111111111111111111111111111111 @
b0 9
b10011100010000 A
b0 <
b0 ;
0(
0-
10
x5
x1
1"
#35
05
01
02
0"
#40
b100111000100000000 B
b1001110001000000 A
b1 ;
1"
#45
0"
#50
b10011100010000000000 B
b100111000100000000 A
b10 ;
1"
#55
0"
#60
b1001110001000000000000 B
b10011100010000000000 A
b11 ;
1"
#65
0"
#70
b100111000100000000000000 B
b1001110001000000000000 A
b100 ;
1"
#75
0"
#80
b10011100010000000000000000 B
b100111000100000000000000 A
b101 ;
1"
#85
0"
#90
b1001110001000000000000000000 B
b10011100010000000000000000 A
b110 ;
1"
#95
0"
#100
b100111000100000000000000000000 B
b1001110001000000000000000000 A
b111 ;
1"
#105
0"
#110
b10011100010000000000000000000000 B
b100111000100000000000000000000 A
b1000 ;
1"
#115
0"
#120
b10 :
b1110001000000000000000000000000 B
b10011100010000000000000000000000 A
b1001 ;
1"
#125
0"
#130
b1 =
b101 :
b11000100000000000000000000000000 B
b1 @
b10 9
b1110001000000000000000000000000 A
b1010 ;
1"
#135
0"
#140
b11 =
b11 :
b10000000000000000000000000000 B
b0 @
b1 <
b101 9
b11000100000000000000000000000000 A
b1011 ;
1"
#145
0"
#150
b110 =
b1100 :
b1000000000000000000000000000000 B
b1111111111111111111111111111110110 @
b11 <
b11 9
b10000000000000000000000000000 A
b1100 ;
1"
#155
0"
#160
b1100 =
b110001 :
b0 B
b1111111111111111111111111111110011 @
b110 <
b1100 9
b1000000000000000000000000000000 A
b1101 ;
1"
#165
0"
#170
b11001 =
b0 :
b0 @
b1100 <
b110001 9
b0 A
b1110 ;
1"
#175
0"
#180
b110010 =
b1111111111111111111111111110011011 @
b11001 <
b0 9
b1111 ;
1"
#185
0"
#190
1!
b0 /
b0 >
b110010 .
b110010 6
b110010 ?
1(
1-
00
1"
#195
12
0"
#200
b11111111111111111111111111001101 3
b110010 #
b110010 +
b110010 4
b110010 7
15
11
1"
#205
05
01
0"
#210
b10110101010 *
b10110101010 8
1)
b100001 %
b10011 &
1'
15
11
1"
#215
05
01
0"
#220
0)
0'
0!
b0 =
b101101010100000 B
b1111111111111111111111111111111111 @
b1011010101000 A
b0 <
b0 ;
0(
0-
10
15
11
1"
#225
05
01
02
0"
#230
b10110101010000000 B
b101101010100000 A
b1 ;
1"
#235
0"
#240
b1011010101000000000 B
b10110101010000000 A
b10 ;
1"
#245
0"
#250
b101101010100000000000 B
b1011010101000000000 A
b11 ;
1"
#255
0"
#260
b10110101010000000000000 B
b101101010100000000000 A
b100 ;
1"
#265
0"
#270
b1011010101000000000000000 B
b10110101010000000000000 A
b101 ;
1"
#275
0"
#280
b101101010100000000000000000 B
b1011010101000000000000000 A
b110 ;
1"
#285
0"
#290
b10110101010000000000000000000 B
b101101010100000000000000000 A
b111 ;
1"
#295
0"
#300
b1011010101000000000000000000000 B
b10110101010000000000000000000 A
b1000 ;
1"
#305
0"
#310
b1 :
b1101010100000000000000000000000 B
b1011010101000000000000000000000 A
b1001 ;
1"
#315
0"
#320
b1 =
b10101010000000000000000000000000 B
b0 @
b1 9
b1101010100000000000000000000000 A
b1010 ;
1"
#325
0"
#330
b10 =
b110 :
b10101000000000000000000000000000 B
b1111111111111111111111111111111100 @
b1 <
b10101010000000000000000000000000 A
b1011 ;
1"
#335
0"
#340
b100 =
b11010 :
b10100000000000000000000000000000 B
b1111111111111111111111111111111101 @
b10 <
b110 9
b10101000000000000000000000000000 A
b1100 ;
1"
#345
0"
#350
b1001 =
b100110 :
b10000000000000000000000000000000 B
b1001 @
b100 <
b11010 9
b10100000000000000000000000000000 A
b1101 ;
1"
#355
0"
#360
b10011 =
b110 :
b0 B
b1 @
b1001 <
b100110 9
b10000000000000000000000000000000 A
b1110 ;
1"
#365
0"
#370
b100110 =
b11000 :
b1111111111111111111111111110111001 @
b10011 <
b110 9
b0 A
b1111 ;
1"
#375
0"
#380
1!
b110 /
b110 >
b100110 .
b100110 6
b100110 ?
1(
1-
00
1"
#385
12
0"
#390
b11111111111111111111111111011001 3
b100110 #
b100110 +
b100110 4
b100110 7
15
11
1"
#395
05
01
0"
#400
b11110100010 *
b11110100010 8
1)
b11011 %
b100011 &
1'
15
11
1"
#405
05
01
0"
#410
0)
0'
0!
b0 =
b0 :
b111101000100000 B
b1111111111111111111111111111111111 @
b0 9
b1111010001000 A
b0 <
b0 ;
0(
0-
10
15
11
1"
#415
05
01
02
0"
#420
b11110100010000000 B
b111101000100000 A
b1 ;
1"
#425
0"
#430
b1111010001000000000 B
b11110100010000000 A
b10 ;
1"
#435
0"
#440
b111101000100000000000 B
b1111010001000000000 A
b11 ;
1"
#445
0"
#450
b11110100010000000000000 B
b111101000100000000000 A
b100 ;
1"
#455
0"
#460
b1111010001000000000000000 B
b11110100010000000000000 A
b101 ;
1"
#465
0"
#470
b111101000100000000000000000 B
b1111010001000000000000000 A
b110 ;
1"
#475
0"
#480
b11110100010000000000000000000 B
b111101000100000000000000000 A
b111 ;
1"
#485
0"
#490
b1111010001000000000000000000000 B
b11110100010000000000000000000 A
b1000 ;
1"
#495
0"
#500
b1 :
b11101000100000000000000000000000 B
b1111010001000000000000000000000 A
b1001 ;
1"
#505
0"
#510
b1 =
b11 :
b10100010000000000000000000000000 B
b0 @
b1 9
b11101000100000000000000000000000 A
b1010 ;
1"
#515
0"
#520
b10 =
b1110 :
b10001000000000000000000000000000 B
b1111111111111111111111111111111110 @
b1 <
b11 9
b10100010000000000000000000000000 A
b1011 ;
1"
#525
0"
#530
b101 =
b10110 :
b100000000000000000000000000000 B
b101 @
b10 <
b1110 9
b10001000000000000000000000000000 A
b1100 ;
1"
#535
0"
#540
b1011 =
b100 :
b10000000000000000000000000000000 B
b1 @
b101 <
b10110 9
b100000000000000000000000000000 A
b1101 ;
1"
#545
0"
#550
b10110 =
b10010 :
b0 B
b1111111111111111111111111111010111 @
b1011 <
b100 9
b10000000000000000000000000000000 A
b1110 ;
1"
#555
0"
#560
b101100 =
b1001000 :
b1111111111111111111111111110111001 @
b10110 <
b10010 9
b0 A
b1111 ;
1"
#565
0"
#570
1!
b10010 /
b10010 >
b101100 .
b101100 6
b101100 ?
1(
1-
00
1"
#575
12
0"
#580
b11111111111111111111111111010011 3
b101100 #
b101100 +
b101100 4
b101100 7
15
11
1"
#585
05
01
0"
#590
b11010110101 *
b11010110101 8
1)
b1110 %
b100111 &
1'
15
11
1"
#595
05
01
0"
#600
0)
0'
0!
b0 =
b0 :
b110101101010000 B
b1111111111111111111111111111111111 @
b0 9
b1101011010100 A
b0 <
b0 ;
0(
0-
10
15
11
1"
#605
05
01
02
0"
#610
b11010110101000000 B
b110101101010000 A
b1 ;
1"
#615
0"
#620
b1101011010100000000 B
b11010110101000000 A
b10 ;
1"
#625
0"
#630
b110101101010000000000 B
b1101011010100000000 A
b11 ;
1"
#635
0"
#640
b11010110101000000000000 B
b110101101010000000000 A
b100 ;
1"
#645
0"
#650
b1101011010100000000000000 B
b11010110101000000000000 A
b101 ;
1"
#655
0"
#660
b110101101010000000000000000 B
b1101011010100000000000000 A
b110 ;
1"
#665
0"
#670
b11010110101000000000000000000 B
b110101101010000000000000000 A
b111 ;
1"
#675
0"
#680
b1101011010100000000000000000000 B
b11010110101000000000000000000 A
b1000 ;
1"
#685
0"
#690
b1 :
b10101101010000000000000000000000 B
b1101011010100000000000000000000 A
b1001 ;
1"
#695
0"
#700
b1 =
b10 :
b10110101000000000000000000000000 B
b0 @
b1 9
b10101101010000000000000000000000 A
b1010 ;
1"
#705
0"
#710
b10 =
b1010 :
b11010100000000000000000000000000 B
b1111111111111111111111111111111101 @
b1 <
b10 9
b10110101000000000000000000000000 A
b1011 ;
1"
#715
0"
#720
b101 =
b111 :
b1010000000000000000000000000000 B
b1 @
b10 <
b1010 9
b11010100000000000000000000000000 A
b1100 ;
1"
#725
0"
#730
b1010 =
b11101 :
b1000000000000000000000000000000 B
b1111111111111111111111111111110010 @
b101 <
b111 9
b1010000000000000000000000000000 A
b1101 ;
1"
#735
0"
#740
b10100 =
b1110101 :
b0 B
b1111111111111111111111111111110100 @
b1010 <
b11101 9
b1000000000000000000000000000000 A
b1110 ;
1"
#745
0"
#750
b101001 =
b10010000 :
b100100 @
b10100 <
b1110101 9
b0 A
b1111 ;
1"
#755
0"
#760
1!
b100100 /
b100100 >
b101001 .
b101001 6
b101001 ?
1(
1-
00
1"
#765
12
0"
#770
b11111111111111111111111111010110 3
b101001 #
b101001 +
b101001 4
b101001 7
15
11
1"
#775
05
01
0"
#780
b1101010010 *
b1101010010 8
1)
b11011 %
b1011 &
1'
15
11
1"
#785
05
01
0"
#790
0)
0'
0!
b0 =
b0 :
b11010100100000 B
b1111111111111111111111111111111111 @
b0 9
b110101001000 A
b0 <
b0 ;
0(
0-
10
15
11
1"
#795
05
01
02
0"
#800
b1101010010000000 B
b11010100100000 A
b1 ;
1"
#805
0"
#810
b110101001000000000 B
b1101010010000000 A
b10 ;
1"
#815
0"
#820
b11010100100000000000 B
b110101001000000000 A
b11 ;
1"
#825
0"
#830
b1101010010000000000000 B
b11010100100000000000 A
b100 ;
1"
#835
0"
#840
b110101001000000000000000 B
b1101010010000000000000 A
b101 ;
1"
#845
0"
#850
b11010100100000000000000000 B
b110101001000000000000000 A
b110 ;
1"
#855
0"
#860
b1101010010000000000000000000 B
b11010100100000000000000000 A
b111 ;
1"
#865
0"
#870
b110101001000000000000000000000 B
b1101010010000000000000000000 A
b1000 ;
1"
#875
0"
#880
b11010100100000000000000000000000 B
b110101001000000000000000000000 A
b1001 ;
1"
#885
0"
#890
b11 :
b1010010000000000000000000000000 B
b11010100100000000000000000000000 A
b1010 ;
1"
#895
0"
#900
b1 =
b1001 :
b1001000000000000000000000000000 B
b10 @
b11 9
b1010010000000000000000000000000 A
b1011 ;
1"
#905
0"
#910
b11 =
b10001 :
b100000000000000000000000000000 B
b100 @
b1 <
b1001 9
b1001000000000000000000000000000 A
b1100 ;
1"
#915
0"
#920
b111 =
b10000 :
b10000000000000000000000000000000 B
b11 <
b10001 9
b100000000000000000000000000000 A
b1101 ;
1"
#925
0"
#930
b1110 =
b1000010 :
b0 B
b1111111111111111111111111111110011 @
b111 <
b10000 9
b10000000000000000000000000000000 A
b1110 ;
1"
#935
0"
#940
b11101 =
b100100 :
b1001 @
b1110 <
b1000010 9
b0 A
b1111 ;
1"
#945
0"
#950
1!
b1001 /
b1001 >
b11101 .
b11101 6
b11101 ?
1(
1-
00
1"
#955
12
0"
#960
b11111111111111111111111111100010 3
b11101 #
b11101 +
b11101 4
b11101 7
15
11
1"
#965
05
01
0"
#970
b10010001101 *
b10010001101 8
1)
b100010 %
b11 &
1'
15
11
1"
#975
05
01
0"
#980
0)
0'
0!
b0 =
b0 :
b100100011010000 B
b1111111111111111111111111111111111 @
b0 9
b1001000110100 A
b0 <
b0 ;
0(
0-
10
15
11
1"
#985
05
01
02
0"
#990
b10010001101000000 B
b100100011010000 A
b1 ;
1"
#995
0"
#1000
b1001000110100000000 B
b10010001101000000 A
b10 ;
1"
#1005
0"
#1010
b100100011010000000000 B
b1001000110100000000 A
b11 ;
1"
#1015
0"
#1020
b10010001101000000000000 B
b100100011010000000000 A
b100 ;
1"
#1025
0"
#1030
b1001000110100000000000000 B
b10010001101000000000000 A
b101 ;
1"
#1035
0"
#1040
b100100011010000000000000000 B
b1001000110100000000000000 A
b110 ;
1"
#1045
0"
#1050
b10010001101000000000000000000 B
b100100011010000000000000000 A
b111 ;
1"
#1055
0"
#1060
b1001000110100000000000000000000 B
b10010001101000000000000000000 A
b1000 ;
1"
#1065
0"
#1070
b1 :
b100011010000000000000000000000 B
b1001000110100000000000000000000 A
b1001 ;
1"
#1075
0"
#1080
b1 =
b0 :
b10001101000000000000000000000000 B
b0 @
b1 9
b100011010000000000000000000000 A
b1010 ;
1"
#1085
0"
#1090
b10 =
b10 :
b110100000000000000000000000000 B
b1111111111111111111111111111111011 @
b1 <
b0 9
b10001101000000000000000000000000 A
b1011 ;
1"
#1095
0"
#1100
b100 =
b1000 :
b11010000000000000000000000000000 B
b1111111111111111111111111111111001 @
b10 <
b10 9
b110100000000000000000000000000 A
b1100 ;
1"
#1105
0"
#1110
b1000 =
b100011 :
b1000000000000000000000000000000 B
b1111111111111111111111111111110111 @
b100 <
b1000 9
b11010000000000000000000000000000 A
b1101 ;
1"
#1115
0"
#1120
b10001 =
b1001 :
b0 B
b10 @
b1000 <
b100011 9
b1000000000000000000000000000000 A
b1110 ;
1"
#1125
0"
#1130
b100010 =
b100100 :
b1111111111111111111111111111000100 @
b10001 <
b1001 9
b0 A
b1111 ;
1"
#1135
0"
#1140
1!
b100010 .
b100010 6
b100010 ?
1(
1-
00
1"
#1145
12
0"
#1150
b11111111111111111111111111011101 3
b100010 #
b100010 +
b100010 4
b100010 7
15
11
1"
#1155
05
01
0"
#1160
b111101010 *
b111101010 8
1)
b10101 %
b111 &
1'
15
11
1"
#1165
05
01
0"
#1170
0)
0'
0!
b0 =
b0 :
b1111010100000 B
b1111111111111111111111111111111111 @
b0 9
b11110101000 A
b0 <
b0 ;
0(
0-
10
15
11
1"
#1175
05
01
02
0"
#1180
b111101010000000 B
b1111010100000 A
b1 ;
1"
#1185
0"
#1190
b11110101000000000 B
b111101010000000 A
b10 ;
1"
#1195
0"
#1200
b1111010100000000000 B
b11110101000000000 A
b11 ;
1"
#1205
0"
#1210
b111101010000000000000 B
b1111010100000000000 A
b100 ;
1"
#1215
0"
#1220
b11110101000000000000000 B
b111101010000000000000 A
b101 ;
1"
#1225
0"
#1230
b1111010100000000000000000 B
b11110101000000000000000 A
b110 ;
1"
#1235
0"
#1240
b111101010000000000000000000 B
b1111010100000000000000000 A
b111 ;
1"
#1245
0"
#1250
b11110101000000000000000000000 B
b111101010000000000000000000 A
b1000 ;
1"
#1255
0"
#1260
b1111010100000000000000000000000 B
b11110101000000000000000000000 A
b1001 ;
1"
#1265
0"
#1270
b1 :
b11101010000000000000000000000000 B
b1111010100000000000000000000000 A
b1010 ;
1"
#1275
0"
#1280
b1 =
b11 :
b10101000000000000000000000000000 B
b0 @
b1 9
b11101010000000000000000000000000 A
b1011 ;
1"
#1285
0"
#1290
b10 =
b1110 :
b10100000000000000000000000000000 B
b1111111111111111111111111111111110 @
b1 <
b11 9
b10101000000000000000000000000000 A
b1100 ;
1"
#1295
0"
#1300
b101 =
b10110 :
b10000000000000000000000000000000 B
b101 @
b10 <
b1110 9
b10100000000000000000000000000000 A
b1101 ;
1"
#1305
0"
#1310
b1011 =
b110 :
b0 B
b1 @
b101 <
b10110 9
b10000000000000000000000000000000 A
b1110 ;
1"
#1315
0"
#1320
b10110 =
b11000 :
b1111111111111111111111111111011001 @
b1011 <
b110 9
b0 A
b1111 ;
1"
#1325
0"
#1330
1!
b110 /
b110 >
b10110 .
b10110 6
b10110 ?
1(
1-
00
1"
#1335
12
0"
#1340
b11111111111111111111111111101001 3
b10110 #
b10110 +
b10110 4
b10110 7
15
11
1"
#1345
05
01
0"
#1350
b10101111010 *
b10101111010 8
1)
b11111 &
1'
15
11
1"
#1355
05
01
0"
#1360
0)
0'
0!
b0 =
b0 :
b101011110100000 B
b1111111111111111111111111111111111 @
b0 9
b1010111101000 A
b0 <
b0 ;
0(
0-
10
15
11
1"
#1365
05
01
02
0"
#1370
b10101111010000000 B
b101011110100000 A
b1 ;
1"
#1375
0"
#1380
b1010111101000000000 B
b10101111010000000 A
b10 ;
1"
#1385
0"
#1390
b101011110100000000000 B
b1010111101000000000 A
b11 ;
1"
#1395
0"
#1400
b10101111010000000000000 B
b101011110100000000000 A
b100 ;
1"
#1405
0"
#1410
b1010111101000000000000000 B
b10101111010000000000000 A
b101 ;
1"
#1415
0"
#1420
b101011110100000000000000000 B
b1010111101000000000000000 A
b110 ;
1"
#1425
0"
#1430
b10101111010000000000000000000 B
b101011110100000000000000000 A
b111 ;
1"
#1435
0"
#1440
b1010111101000000000000000000000 B
b10101111010000000000000000000 A
b1000 ;
1"
#1445
0"
#1450
b1 :
b1011110100000000000000000000000 B
b1010111101000000000000000000000 A
b1001 ;
1"
#1455
0"
#1460
b1 =
b1111010000000000000000000000000 B
b0 @
b1 9
b1011110100000000000000000000000 A
b1010 ;
1"
#1465
0"
#1470
b10 =
b101 :
b11101000000000000000000000000000 B
b1111111111111111111111111111111100 @
b1 <
b1111010000000000000000000000000 A
b1011 ;
1"
#1475
0"
#1480
b100 =
b10111 :
b10100000000000000000000000000000 B
b10 <
b101 9
b11101000000000000000000000000000 A
b1100 ;
1"
#1485
0"
#1490
b1001 =
b11010 :
b10000000000000000000000000000000 B
b110 @
b100 <
b10111 9
b10100000000000000000000000000000 A
b1101 ;
1"
#1495
0"
#1500
b10010 =
b1101010 :
b0 B
b1111111111111111111111111111110101 @
b1001 <
b11010 9
b10000000000000000000000000000000 A
b1110 ;
1"
#1505
0"
#1510
b100101 =
b10000100 :
b100001 @
b10010 <
b1101010 9
b0 A
b1111 ;
1"
#1515
0"
#1520
1!
b100001 /
b100001 >
b100101 .
b100101 6
b100101 ?
1(
1-
00
1"
#1525
12
0"
#1530
b11111111111111111111111111011010 3
b100101 #
b100101 +
b100101 4
b100101 7
15
11
1"
#1535
05
01
0"
#1540
b1010000000 *
b1010000000 8
1)
b11000 %
b1000 &
1'
15
11
1"
#1545
05
01
0"
#1550
0)
0'
0!
b0 =
b0 :
b10100000000000 B
b1111111111111111111111111111111111 @
b0 9
b101000000000 A
b0 <
b0 ;
0(
0-
10
15
11
1"
#1555
05
01
02
0"
#1560
b1010000000000000 B
b10100000000000 A
b1 ;
1"
#1565
0"
#1570
b101000000000000000 B
b1010000000000000 A
b10 ;
1"
#1575
0"
#1580
b10100000000000000000 B
b101000000000000000 A
b11 ;
1"
#1585
0"
#1590
b1010000000000000000000 B
b10100000000000000000 A
b100 ;
1"
#1595
0"
#1600
b101000000000000000000000 B
b1010000000000000000000 A
b101 ;
1"
#1605
0"
#1610
b10100000000000000000000000 B
b101000000000000000000000 A
b110 ;
1"
#1615
0"
#1620
b1010000000000000000000000000 B
b10100000000000000000000000 A
b111 ;
1"
#1625
0"
#1630
b101000000000000000000000000000 B
b1010000000000000000000000000 A
b1000 ;
1"
#1635
0"
#1640
b10100000000000000000000000000000 B
b101000000000000000000000000000 A
b1001 ;
1"
#1645
0"
#1650
b10 :
b10000000000000000000000000000000 B
b10100000000000000000000000000000 A
b1010 ;
1"
#1655
0"
#1660
b1 =
b110 :
b0 B
b1 @
b10 9
b10000000000000000000000000000000 A
b1011 ;
1"
#1665
0"
#1670
b11 =
b100 :
b1 <
b110 9
b0 A
b1100 ;
1"
#1675
0"
#1680
b110 =
b10000 :
b1111111111111111111111111111110111 @
b11 <
b100 9
b1101 ;
1"
#1685
0"
#1690
b1100 =
b1000000 :
b110 <
b10000 9
b1110 ;
1"
#1695
0"
#1700
b11001 =
b111100 :
b1111 @
b1100 <
b1000000 9
b1111 ;
1"
#1705
0"
#1710
1!
b1111 /
b1111 >
b11001 .
b11001 6
b11001 ?
1(
1-
00
1"
#1715
12
0"
#1720
b11111111111111111111111111100110 3
b11001 #
b11001 +
b11001 4
b11001 7
15
11
1"
#1725
05
01
0"
#1730
b1101101101 *
b1101101101 8
1)
b11101 %
b110 &
1'
15
11
1"
#1735
05
01
0"
#1740
0)
0'
0!
b0 =
b0 :
b11011011010000 B
b1111111111111111111111111111111111 @
b0 9
b110110110100 A
b0 <
b0 ;
0(
0-
10
15
11
1"
#1745
05
01
02
0"
#1750
b1101101101000000 B
b11011011010000 A
b1 ;
1"
#1755
0"
#1760
b110110110100000000 B
b1101101101000000 A
b10 ;
1"
#1765
0"
#1770
b11011011010000000000 B
b110110110100000000 A
b11 ;
1"
#1775
0"
#1780
b1101101101000000000000 B
b11011011010000000000 A
b100 ;
1"
#1785
0"
#1790
b110110110100000000000000 B
b1101101101000000000000 A
b101 ;
1"
#1795
0"
#1800
b11011011010000000000000000 B
b110110110100000000000000 A
b110 ;
1"
#1805
0"
#1810
b1101101101000000000000000000 B
b11011011010000000000000000 A
b111 ;
1"
#1815
0"
#1820
b110110110100000000000000000000 B
b1101101101000000000000000000 A
b1000 ;
1"
#1825
0"
#1830
b11011011010000000000000000000000 B
b110110110100000000000000000000 A
b1001 ;
1"
#1835
0"
#1840
b11 :
b1101101000000000000000000000000 B
b11011011010000000000000000000000 A
b1010 ;
1"
#1845
0"
#1850
b1 =
b1001 :
b10110100000000000000000000000000 B
b10 @
b11 9
b1101101000000000000000000000000 A
b1011 ;
1"
#1855
0"
